[
  {"permit":"BR-25-10084","address":"259 Kendrick St","applied":"","issued":"2/18/25","status":"Issued","cost":0,"sqft":481,"type":"Internal","contractor":"DIY (Homeowner)","notes":"Garage conversion to ADU. 481sf conditioned space."},
  {"permit":"BR-24-11197","address":"70 Standish Rd","applied":"","issued":"2/18/25","status":"Issued","cost":0,"sqft":900,"type":"Internal","contractor":"Om Builders LLC","notes":"Basement remodel to ADU. 900sf. Owner occupied."},
  {"permit":"BR-25-10416","address":"61 Grant St","applied":"","issued":"6/13/25","status":"Active","cost":68514,"sqft":0,"type":"Internal","contractor":"Robert P Way","notes":"Remodel existing finished basement to in-law ADU."}
]
